rankfmc/__init__.py
rankfmc/_rankfm.cpython-311-darwin.so
rankfmc/evaluation.py
rankfmc/rankfm.py
rankfmc/utils.py
rankfmc-0.3.3.dist-info/licenses/LICENSE
rankfmc-0.3.3.dist-info/METADATA
rankfmc-0.3.3.dist-info/WHEEL
rankfmc-0.3.3.dist-info/top_level.txt
rankfmc-0.3.3.dist-info/RECORD
