Metadata-Version: 2.4
Name: rankfmc
Version: 0.3.3
Summary: a python implementation of the generic factorization machines model class adapted for collaborative filtering recommendation problems with implicit feedback user-item interaction data and (optionally) additional user/item side features
Home-page: https://github.com/ErraticO/rankfmc
Author: ErraticO
Author-email: wyh123132@163.com
License: GNU General Public License v3.0
Keywords: machine,learning,recommendation,factorization,machines,implicit
Requires-Python: >=3.8
License-File: LICENSE
Requires-Dist: numpy>=1.15
Requires-Dist: pandas>=0.24
Dynamic: author
Dynamic: author-email
Dynamic: description
Dynamic: description-content-type
Dynamic: home-page
Dynamic: keywords
Dynamic: license
Dynamic: license-file
Dynamic: requires-dist
Dynamic: requires-python
Dynamic: summary
